jp_number/__init__.py
jp_number/jp_number.py
jp_number/versions.py
jp_number-0.1.1.dist-info/LICENSE
jp_number-0.1.1.dist-info/METADATA
jp_number-0.1.1.dist-info/WHEEL
jp_number-0.1.1.dist-info/top_level.txt
jp_number-0.1.1.dist-info/RECORD
