Metadata-Version: 2.1
Name: jp-number
Version: 0.1.1
Summary: Convert numbers from/to Japanese Numbers
Home-page: https://github.com/iisaka51/jp_number
Author: iisaka51
Author-email: iisaka51@gmail.com
License: MIT
Platform: UNKNOWN
Classifier: License :: OSI Approved :: MIT License
Classifier: Programming Language :: Python :: 3.8
Classifier: Programming Language :: Python :: 3.9
Classifier: Programming Language :: Python :: 3.10
License-File: LICENSE
